github_webhook2-0.0.3.data/scripts/startwebhook
webhook/__init__.py
webhook/webhook.py
github_webhook2-0.0.3.dist-info/METADATA
github_webhook2-0.0.3.dist-info/WHEEL
github_webhook2-0.0.3.dist-info/top_level.txt
github_webhook2-0.0.3.dist-info/RECORD
