Metadata-Version: 2.1
Name: github-webhook2
Version: 0.0.3
Summary: github webhook
Home-page: https://github.com/drunkpig/githubwebhook
Author: drunkpig
Author-email: xuchaoo@gmail.com
License: UNKNOWN
Platform: UNKNOWN
Classifier: Programming Language :: Python :: 3
Classifier: License :: OSI Approved :: MIT License
Classifier: Operating System :: OS Independent
Requires-Python: >=3.7
Requires-Dist: flask
